bkflow/__init__.py
bkflow/client/__init__.py
bkflow/client/base.py
bkflow/client/core.py
bkflow/client/apis/__init__.py
bkflow/client/apis/bkflow.py
bkflow/common/__init__.py
bkflow/common/decorators.py
bkflow/common/exceptions.py
bkflow/common/loader.py
bkflow/common/validator.py
bkflow/common/views.py
bkflow/config/__init__.py
bkflow/config/default.py
bkflow/interface/__init__.py
bkflow/interface/apps.py
bkflow/interface/serializers.py
bkflow/interface/signals.py
bkflow/interface/urls.py
bkflow/interface/utils.py
bkflow/interface/views.py
bkflow_sdk-0.0.44.dist-info/licenses/LICENSE
bkflow_sdk-0.0.44.dist-info/WHEEL
bkflow_sdk-0.0.44.dist-info/METADATA
bkflow_sdk-0.0.44.dist-info/RECORD
