Metadata-Version: 2.4
Name: bkflow-sdk
Version: 0.0.44
Summary: A Django app to provide bkflow interface api.
Author-email: blueking <blueking@tencent.com>
License-File: LICENSE
Requires-Dist: Django >=3.2, <6
Requires-Dist: djangorestframework >= 3.14, <4
Requires-Dist: drf-yasg >= 1.20.0, <2
Requires-Dist: requests >= 2.28.2, <3
Requires-Dist: pytest >=7.0.1,<8 ; extra == "test"
Requires-Dist: pytest-django>=4.5.2,<5.0 ; extra == "test"
Requires-Dist: pytest-cov>=4.0.0 ; extra == "test"
Requires-Dist: djangorestframework >3, <4 ; extra == "test"
Project-URL: Home, https://github.com/TencentBlueKing/bkflow-sdk
Provides-Extra: test
